phishdetect/__init__.py
phishdetect/endpoints.py
phishdetect/phishdetect.py
phishdetect/validate.py
phishdetect/__pycache__/__init__.cpython-39.pyc
phishdetect/__pycache__/endpoints.cpython-39.pyc
phishdetect/__pycache__/phishdetect.cpython-39.pyc
phishdetect/__pycache__/validate.cpython-39.pyc
phishdetect/models/__init__.py
phishdetect/models/alerts.py
phishdetect/models/analyze.py
phishdetect/models/indicators.py
phishdetect/models/model.py
phishdetect/models/reports.py
phishdetect/models/users.py
phishdetect/models/__pycache__/__init__.cpython-39.pyc
phishdetect/models/__pycache__/alerts.cpython-39.pyc
phishdetect/models/__pycache__/analyze.cpython-39.pyc
phishdetect/models/__pycache__/indicators.cpython-39.pyc
phishdetect/models/__pycache__/model.cpython-39.pyc
phishdetect/models/__pycache__/reports.cpython-39.pyc
phishdetect/models/__pycache__/users.cpython-39.pyc
phishdetect-1.10.0.data/scripts/phishdetect-cli
phishdetect-1.10.0.dist-info/LICENSE
phishdetect-1.10.0.dist-info/METADATA
phishdetect-1.10.0.dist-info/WHEEL
phishdetect-1.10.0.dist-info/top_level.txt
phishdetect-1.10.0.dist-info/RECORD
