Metadata-Version: 2.1
Name: phishdetect
Version: 1.10.0
Summary: This is a Python3 library and CLI tool to easily interact with a PhishDetect Node API server
Home-page: UNKNOWN
Author: Claudio Guarnieri
Author-email: nex@nex.sx
License: MIT
Keywords: security phishing phishdetect
Platform: UNKNOWN
Requires-Dist: click
Requires-Dist: requests
